bonfire/__init__.py
bonfire/bonfire.py
bonfire/config.py
bonfire/configmaps.py
bonfire/elastic_logging.py
bonfire/local.py
bonfire/namespaces.py
bonfire/openshift.py
bonfire/processor.py
bonfire/qontract.py
bonfire/secrets.py
bonfire/utils.py
bonfire/resources/default-iqe-cji.yaml
bonfire/resources/default_config.yaml
bonfire/resources/local-cluster-clowdenvironment.yaml
bonfire/resources/reservation-template.yaml
crc_bonfire-6.7.2.dist-info/METADATA
crc_bonfire-6.7.2.dist-info/WHEEL
crc_bonfire-6.7.2.dist-info/entry_points.txt
crc_bonfire-6.7.2.dist-info/top_level.txt
crc_bonfire-6.7.2.dist-info/RECORD
