Metadata-Version: 2.4
Name: crc-bonfire
Version: 6.7.2
Summary: A CLI tool used to deploy ephemeral environments for testing cloud.redhat.com applications
Author-email: Brandon Squizzato <bsquizza@redhat.com>
License: MIT License
Project-URL: Homepage, https://www.github.com/RedHatInsights/bonfire
Classifier: License :: OSI Approved :: MIT License
Classifier: Programming Language :: Python
Classifier: Programming Language :: Python :: 3
Classifier: Programming Language :: Python :: 3.8
Classifier: Programming Language :: Python :: 3.9
Classifier: Programming Language :: Python :: 3.10
Classifier: Programming Language :: Python :: 3.11
Classifier: Programming Language :: Python :: 3.12
Classifier: Topic :: Utilities
Requires-Python: >=3.6
Requires-Dist: app-common-python>=0.1.6
Requires-Dist: cached_property
Requires-Dist: chardet<5.3,>=5.2
Requires-Dist: click>=7.1.2
Requires-Dist: gql[requests]>=3.5.0
Requires-Dist: importlib-metadata; python_version < "3.8"
Requires-Dist: importlib-resources; python_version < "3.9"
Requires-Dist: junitparser
Requires-Dist: multidict
Requires-Dist: ocviapy>=1.5.0
Requires-Dist: python-dotenv
Requires-Dist: PyYAML
Requires-Dist: requests
Requires-Dist: sh
Requires-Dist: tabulate
Requires-Dist: wait-for
Requires-Dist: packaging
Provides-Extra: test
Requires-Dist: mock; extra == "test"
Requires-Dist: pytest; extra == "test"
Requires-Dist: pytest-mock; extra == "test"
Requires-Dist: requests-mock; extra == "test"
